spymx_kernels/__init__.py
spymx_kernels/_version.py
spymx_kernels/start_kernel.py
spymx_kernels/console/__init__.py
spymx_kernels/console/__main__.py
spymx_kernels/console/kernel.py
spymx_kernels/console/kernel_5.py
spymx_kernels/console/start.py
spymx_kernels/utility/__init__.py
spymx_kernels/utility/tupleencoder.py
spymx_kernels/utility/typeutil.py
spymx_kernels-0.2.3.dist-info/licenses/LICENSE.GPL.txt
spymx_kernels-0.2.3.dist-info/licenses/LICENSE.txt
spymx_kernels-0.2.3.dist-info/METADATA
spymx_kernels-0.2.3.dist-info/WHEEL
spymx_kernels-0.2.3.dist-info/top_level.txt
spymx_kernels-0.2.3.dist-info/RECORD
