Metadata-Version: 2.4
Name: spymx-kernels
Version: 0.2.3
Summary: Jupyter kernels for Spyder plugin for modelx
Home-page: https://github.com/fumitoh/spymx-kernels
Download-URL: https://pypi.org/project/spymx-kernels
Author: Fumito Hamamura
Author-email: fumito.ham@gmail.com
License: LGPLv3
Keywords: modelx spyder jupyter kernel ipython console
Classifier: Development Status :: 5 - Production/Stable
Classifier: Framework :: Jupyter
Classifier: Framework :: IPython
Classifier: Intended Audience :: Developers
Classifier: License :: OSI Approved :: GNU Lesser General Public License v3 (LGPLv3)
Classifier: Operating System :: OS Independent
Classifier: Programming Language :: Python :: 3
Classifier: Programming Language :: Python :: 3.7
Classifier: Programming Language :: Python :: 3.8
Classifier: Programming Language :: Python :: 3.9
Classifier: Programming Language :: Python :: 3.10
Classifier: Programming Language :: Python :: 3.11
Classifier: Programming Language :: Python :: 3.12
Classifier: Programming Language :: Python :: 3.13
Classifier: Topic :: Software Development :: Interpreters
License-File: LICENSE.GPL.txt
License-File: LICENSE.txt
Requires-Dist: spyder-kernels>=1.8.1
Provides-Extra: test
Dynamic: author
Dynamic: author-email
Dynamic: classifier
Dynamic: description
Dynamic: description-content-type
Dynamic: download-url
Dynamic: home-page
Dynamic: keywords
Dynamic: license
Dynamic: license-file
Dynamic: provides-extra
Dynamic: requires-dist
Dynamic: summary
